MANIFEST.in
README.txt
setup.cfg
setup.py
docs/HISTORY.txt
docs/INSTALL.txt
docs/LICENSE.GPL
docs/LICENSE.txt
docs/screen.png
wpd/__init__.py
wpd.mmxi.countdown.egg-info/PKG-INFO
wpd.mmxi.countdown.egg-info/SOURCES.txt
wpd.mmxi.countdown.egg-info/dependency_links.txt
wpd.mmxi.countdown.egg-info/entry_points.txt
wpd.mmxi.countdown.egg-info/namespace_packages.txt
wpd.mmxi.countdown.egg-info/not-zip-safe
wpd.mmxi.countdown.egg-info/requires.txt
wpd.mmxi.countdown.egg-info/top_level.txt
wpd/mmxi/__init__.py
wpd/mmxi/countdown/README.txt
wpd/mmxi/countdown/__init__.py
wpd/mmxi/countdown/config.py
wpd/mmxi/countdown/configure.zcml
wpd/mmxi/countdown/setuphandlers.py
wpd/mmxi/countdown/version.txt
wpd/mmxi/countdown/browser/__init__.py
wpd/mmxi/countdown/browser/configure.zcml
wpd/mmxi/countdown/browser/wpd-logo.gif
wpd/mmxi/countdown/browser/wpdcountdown.pt
wpd/mmxi/countdown/browser/wpdcountdown.py
wpd/mmxi/countdown/docs/__init__.py
wpd/mmxi/countdown/docs/browser.txt
wpd/mmxi/countdown/interfaces/__init__.py
wpd/mmxi/countdown/locales/manual.pot
wpd/mmxi/countdown/locales/rebuildAll.sh
wpd/mmxi/countdown/locales/wpd.mmxi.countdown.pot
wpd/mmxi/countdown/locales/pt_BR/LC_MESSAGES/wpd.mmxi.countdown.po
wpd/mmxi/countdown/profiles/default/import_steps.xml
wpd/mmxi/countdown/profiles/default/metadata.xml
wpd/mmxi/countdown/profiles/default/portlets.xml
wpd/mmxi/countdown/profiles/default/wpd.mmxi.countdown.txt
wpd/mmxi/countdown/tests/__init__.py
wpd/mmxi/countdown/tests/base.py
wpd/mmxi/countdown/tests/test_portlet.py
wpd/mmxi/countdown/upgrades/__init__.py
wpd/mmxi/countdown/upgrades/configure.zcml
wpd/mmxi/countdown/upgrades/to01.py