Metadata-Version: 1.0
Name: wpd.mmxi.countdown
Version: 1.0
Summary: Countdown portlet for the World Plone Day 2011
Home-page: http://svn.plone.org/svn/collective/
Author: Simples Consultoria
Author-email: products@simplesconsultoria.com.br
License: GPL
Keywords: plone worldploneday wpd countdown portlet
Platform: UNKNOWN
Classifier: Framework :: Plone
Classifier: Framework :: Zope2
Classifier: Framework :: Zope3
Classifier: Programming Language :: Python
Classifier: Topic :: Software Development :: Libraries :: Python Modules
